{
  "header": {
    "version": 4,
    "description": "Karaoke Mugen Karaoke Data File"
  },
  "medias": [
    {
      "version": "Default",
      "filename": "SPA - ROBERTO CARLOS - - ROBERTO CARLOS - SIMBOLO SEXUAL.MP3",
      "loudnorm": "-15.51,0.01,3.90,-25.67,-0.42",
      "duration": 289,
      "default": true,
      "lyrics": [
        {
          "filename": "SPA - ROBERTO CARLOS - - ROBERTO CARLOS - SIMBOLO SEXUAL.cdg",
          "default": true,
          "version": "Default"
        }
      ]
    }
  ],
  "data": {
    "kid": "2a1db3b7-9d7a-420b-99be-c75d9e0b4ad8",
    "title": "ROBERTO CARLOS   -   SIMBOLO SEXUAL",
    "titles": {
      "spa": "ROBERTO CARLOS   -   SIMBOLO SEXUAL"
    },
    "titles_default_language": "spa",
    "year": 2021,
    "tags": {
      "authors": [
        "2dda142a-cd18-4e83-a037-25ad3d9e771a"
      ],
      "songtypes": [
        "14a2f35e-849e-4e69-a9a6-ed042b07f7bc"
      ],
      "singers": [
        "23a91bf4-864a-4218-a2ae-d42106fdff92"
      ],
      "collections": [
        "6ec1bc16-d8d2-4617-8643-a837c2987868"
      ],
      "langs": [
        "11e9665f-f813-4495-bced-7ef9422cc992"
      ]
    },
    "created_at": "2022-11-03T12:32:47.006Z",
    "modified_at": "2022-11-03T12:32:47.683Z",
    "repository": "Local",
    "subfile": {
      "error": false,
      "size": 4631791,
      "gain": -2.06,
      "duration": 289,
      "loudnorm": "-15.51,0.01,3.90,-25.67,-0.42",
      "filename": "processed_b023be44836c7123470ae4b3b0cf8629.MP3"
    },
    "mediafile": {
      "error": false,
      "size": 4631791,
      "gain": -2.06,
      "duration": 289,
      "loudnorm": "-15.51,0.01,3.90,-25.67,-0.42",
      "filename": "processed_2c4e21d9cce0b9e543486c56fb8b8987.MP3"
    },
    "mediafileIsTouched": false,
    "subfileIsTouched": false,
    "repositoriesValue": null,
    "repoToCopySong": null,
    "comment": "batch",
    "karaSearch": [],
    "parentKara": null,
    "errors": []
  }
}