{
  "header": {
    "version": 4,
    "description": "Karaoke Mugen Karaoke Data File"
  },
  "medias": [
    {
      "version": "Default",
      "filename": "SPA - Anthony Santos & Vakero - - VA - 04 - El Ultimo Adios.mp3",
      "loudnorm": "-10.28,1.33,6.20,-20.70,-0.92",
      "duration": 276,
      "default": true,
      "lyrics": [
        {
          "filename": "SPA - Anthony Santos & Vakero - - VA - 04 - El Ultimo Adios.cdg",
          "default": true,
          "version": "Default"
        }
      ]
    }
  ],
  "data": {
    "kid": "892956b1-239f-48e8-af7a-f7c7f87d101d",
    "title": "VA - 04 - El Ultimo Adios",
    "titles": {
      "spa": "VA - 04 - El Ultimo Adios"
    },
    "titles_default_language": "spa",
    "year": 2021,
    "tags": {
      "authors": [
        "2dda142a-cd18-4e83-a037-25ad3d9e771a"
      ],
      "songtypes": [
        "14a2f35e-849e-4e69-a9a6-ed042b07f7bc"
      ],
      "singers": [
        "bf66762f-69f7-4fd3-a45c-2bff7b2a272f"
      ],
      "collections": [
        "6ec1bc16-d8d2-4617-8643-a837c2987868"
      ],
      "langs": [
        "11e9665f-f813-4495-bced-7ef9422cc992"
      ]
    },
    "created_at": "2022-11-03T13:32:42.721Z",
    "modified_at": "2022-11-03T13:32:43.147Z",
    "repository": "Local",
    "subfile": {
      "error": true,
      "size": null,
      "gain": null,
      "loudnorm": null,
      "duration": null,
      "filename": "processed_ddc6a401db40c9f4e22280b6dee0c839.cdg"
    },
    "mediafile": {
      "error": false,
      "size": 6642842,
      "gain": -7.92,
      "duration": 276,
      "loudnorm": "-10.28,1.33,6.20,-20.70,-0.92",
      "filename": "processed_02f03c3051ab609a9631587f37881c3a.mp3"
    },
    "mediafileIsTouched": false,
    "subfileIsTouched": false,
    "repositoriesValue": null,
    "repoToCopySong": null,
    "comment": "batch",
    "karaSearch": [],
    "parentKara": null,
    "errors": []
  }
}