{
  "header": {
    "version": 4,
    "description": "Karaoke Mugen Karaoke Data File"
  },
  "medias": [
    {
      "version": "Default",
      "filename": "SPA - JULIO IGLECIAS - - Julio Iglesias- Caminito.mp3",
      "loudnorm": "-16.47,-0.84,4.90,-26.51,-0.45",
      "duration": 145,
      "default": true,
      "lyrics": [
        {
          "filename": "SPA - JULIO IGLECIAS - - Julio Iglesias- Caminito.cdg",
          "default": true,
          "version": "Default"
        }
      ]
    }
  ],
  "data": {
    "kid": "3f5159ec-2893-4d56-a3b6-1f341b90c9e3",
    "title": "Julio Iglesias- Caminito",
    "titles": {
      "spa": "Julio Iglesias- Caminito"
    },
    "titles_default_language": "spa",
    "year": 2021,
    "tags": {
      "authors": [
        "2dda142a-cd18-4e83-a037-25ad3d9e771a"
      ],
      "songtypes": [
        "14a2f35e-849e-4e69-a9a6-ed042b07f7bc"
      ],
      "singers": [
        "a539fb0a-fecc-42e4-ab13-bdbf2b7297f5"
      ],
      "collections": [
        "6ec1bc16-d8d2-4617-8643-a837c2987868"
      ],
      "langs": [
        "11e9665f-f813-4495-bced-7ef9422cc992"
      ]
    },
    "created_at": "2022-11-03T08:02:28.000Z",
    "modified_at": "2022-11-03T08:02:28.405Z",
    "repository": "Local",
    "subfile": {
      "error": true,
      "size": null,
      "gain": null,
      "loudnorm": null,
      "duration": null,
      "filename": "processed_d96cea4232533f864c5843b043ebffa8.cdg"
    },
    "mediafile": {
      "error": false,
      "size": 2333561,
      "gain": -1.31,
      "duration": 145,
      "loudnorm": "-16.47,-0.84,4.90,-26.51,-0.45",
      "filename": "processed_98ca7db95d4e869f52d7ccffd4ef11fd.mp3"
    },
    "mediafileIsTouched": false,
    "subfileIsTouched": false,
    "repositoriesValue": null,
    "repoToCopySong": null,
    "comment": "batch",
    "karaSearch": [],
    "parentKara": null,
    "errors": []
  }
}