{
  "header": {
    "version": 4,
    "description": "Karaoke Mugen Karaoke Data File"
  },
  "medias": [
    {
      "version": "Default",
      "filename": "SPA - Christian Castro - - Christian Castro - Si tu me amaras.mp3",
      "loudnorm": "-8.84,7.61,12.20,-19.19,-2.33",
      "duration": 270,
      "default": true,
      "lyrics": [
        {
          "filename": "SPA - Christian Castro - - Christian Castro - Si tu me amaras.cdg",
          "default": true,
          "version": "Default"
        }
      ]
    }
  ],
  "data": {
    "kid": "cb06789d-8292-43ad-9af7-f6401df79608",
    "title": "Christian Castro - Si tu me amaras",
    "titles": {
      "spa": "Christian Castro - Si tu me amaras"
    },
    "titles_default_language": "spa",
    "year": 2021,
    "tags": {
      "authors": [
        "2dda142a-cd18-4e83-a037-25ad3d9e771a"
      ],
      "songtypes": [
        "14a2f35e-849e-4e69-a9a6-ed042b07f7bc"
      ],
      "singers": [
        "27dd2042-d853-49be-87b4-70122a2b96b9"
      ],
      "collections": [
        "6ec1bc16-d8d2-4617-8643-a837c2987868"
      ],
      "langs": [
        "11e9665f-f813-4495-bced-7ef9422cc992"
      ]
    },
    "created_at": "2022-11-03T03:29:14.681Z",
    "modified_at": "2022-11-03T03:29:15.107Z",
    "repository": "Local",
    "subfile": {
      "error": true,
      "size": null,
      "gain": null,
      "loudnorm": null,
      "duration": null,
      "filename": "processed_bdb3d139c64869509009424b34833408.cdg"
    },
    "mediafile": {
      "error": false,
      "size": 6503120,
      "gain": -9.51,
      "duration": 270,
      "loudnorm": "-8.84,7.61,12.20,-19.19,-2.33",
      "filename": "processed_6f1572a9d1c1dfef55e40846b365abeb.mp3"
    },
    "mediafileIsTouched": false,
    "subfileIsTouched": false,
    "repositoriesValue": null,
    "repoToCopySong": null,
    "comment": "batch",
    "karaSearch": [],
    "parentKara": null,
    "errors": []
  }
}