{
  "header": {
    "version": 4,
    "description": "Karaoke Mugen Karaoke Data File"
  },
  "medias": [
    {
      "version": "Default",
      "filename": "SPA - YOSKAR SARANTE - - YOSCAR SARANTE - PERDOMAME.MP3",
      "loudnorm": "-14.14,0.80,2.60,-24.25,-0.39",
      "duration": 284,
      "default": true,
      "lyrics": [
        {
          "filename": "SPA - YOSKAR SARANTE - - YOSCAR SARANTE - PERDOMAME.cdg",
          "default": true,
          "version": "Default"
        }
      ]
    }
  ],
  "data": {
    "kid": "bb3a155a-2bd5-4292-9ed3-7eb8cd2ec31f",
    "title": "YOSCAR SARANTE   -   PERDOMAME",
    "titles": {
      "spa": "YOSCAR SARANTE   -   PERDOMAME"
    },
    "titles_default_language": "spa",
    "year": 2021,
    "tags": {
      "authors": [
        "2dda142a-cd18-4e83-a037-25ad3d9e771a"
      ],
      "songtypes": [
        "c770d7d4-2b4f-48a3-88e8-d24414a60cec"
      ],
      "singers": [
        "f097b81f-76c8-47d1-ad4d-3a3bc3945ec1"
      ],
      "collections": [
        "6ec1bc16-d8d2-4617-8643-a837c2987868"
      ],
      "langs": [
        "11e9665f-f813-4495-bced-7ef9422cc992"
      ]
    },
    "created_at": "2022-11-02T20:00:56.373Z",
    "modified_at": "2022-11-02T20:00:57.280Z",
    "repository": "Local",
    "subfile": {
      "error": false,
      "size": 4551543,
      "gain": -3.78,
      "duration": 284,
      "loudnorm": "-14.14,0.80,2.60,-24.25,-0.39",
      "filename": "processed_19ca494e2b586203045d534c6e32306f.MP3"
    },
    "mediafile": {
      "error": false,
      "size": 4551543,
      "gain": -3.78,
      "duration": 284,
      "loudnorm": "-14.14,0.80,2.60,-24.25,-0.39",
      "filename": "processed_a67da1d8bf6296462eddde381e97166d.MP3"
    },
    "mediafileIsTouched": false,
    "subfileIsTouched": false,
    "repositoriesValue": null,
    "repoToCopySong": null,
    "comment": "batch",
    "karaSearch": [],
    "parentKara": null,
    "errors": []
  }
}