{
  "header": {
    "version": 4,
    "description": "Karaoke Mugen Karaoke Data File"
  },
  "medias": [
    {
      "version": "Default",
      "filename": "SPA - Gabriel, Juan - - Juan Gabriel - Ases Y Tercia De Reyes.mp3",
      "loudnorm": "-11.76,0.45,4.30,-21.95,0.05",
      "duration": 114,
      "default": true,
      "lyrics": [
        {
          "filename": "SPA - Gabriel, Juan - - Juan Gabriel - Ases Y Tercia De Reyes.cdg",
          "default": true,
          "version": "Default"
        }
      ]
    }
  ],
  "data": {
    "kid": "75babcb0-920c-4a9d-b942-7265944eb484",
    "title": "Juan Gabriel - Ases Y Tercia De Reyes",
    "titles": {
      "spa": "Juan Gabriel - Ases Y Tercia De Reyes"
    },
    "titles_default_language": "spa",
    "year": 2021,
    "tags": {
      "authors": [
        "2dda142a-cd18-4e83-a037-25ad3d9e771a"
      ],
      "songtypes": [
        "14a2f35e-849e-4e69-a9a6-ed042b07f7bc"
      ],
      "singers": [
        "aa9513d1-bf2c-4478-8b3a-43f0b6febceb"
      ],
      "collections": [
        "6ec1bc16-d8d2-4617-8643-a837c2987868"
      ],
      "langs": [
        "11e9665f-f813-4495-bced-7ef9422cc992"
      ]
    },
    "created_at": "2022-11-03T07:43:36.589Z",
    "modified_at": "2022-11-03T07:43:36.989Z",
    "repository": "Local",
    "subfile": {
      "error": true,
      "size": null,
      "gain": null,
      "loudnorm": null,
      "duration": null,
      "filename": "processed_54065e151205fbcfc2290a23f2765559.cdg"
    },
    "mediafile": {
      "error": false,
      "size": 2756327,
      "gain": -6.77,
      "duration": 114,
      "loudnorm": "-11.76,0.45,4.30,-21.95,0.05",
      "filename": "processed_88c290fc0faf3d15b0f7b55509d65ee7.mp3"
    },
    "mediafileIsTouched": false,
    "subfileIsTouched": false,
    "repositoriesValue": null,
    "repoToCopySong": null,
    "comment": "batch",
    "karaSearch": [],
    "parentKara": null,
    "errors": []
  }
}